aiobtcrpc/__init__.py
aiobtcrpc/bitcoin_core_client.py
tests/__init__.py
tests/test_bitcoin_core_client.py
aiobtcrpc-0.1.1.dist-info/LICENSE.md
aiobtcrpc-0.1.1.dist-info/METADATA
aiobtcrpc-0.1.1.dist-info/WHEEL
aiobtcrpc-0.1.1.dist-info/top_level.txt
aiobtcrpc-0.1.1.dist-info/RECORD
