Metadata-Version: 2.1
Name: aiobtcrpc
Version: 0.1.1
Summary: Asynchronous Bitcoin RPC Client
Home-page: https://github.com/biobdeveloper/aiobtcrpc
Author: @biobdeveloper
License: MIT
Platform: UNKNOWN
Requires-Python: >=3.8
Requires-Dist: aiohttp (==3.7.3)
